{
  "id": "triatower",
  "meta": {
    "건물명": "제2판교 트라이타워",
    "주소": "경기도 성남시 수정구 금토동 714",
    "대상공간": "1F 101~103호",
    "전용면적PY": 74.76,
    "준공일": "2025-02",
    "분석일": "2026-04-14"
  },
  "임대조건": {
    "보증금": 90000000,
    "월MG": 7500000,
    "관리비": 2990000
  },
  "포획시장": {
    "단지전체상주": 20458,
    "입주완료": 13893,
    "입주예정": 6565,
    "트라이타워자체": 1200,
    "현재입주율": 68,
    "출근율": 85,
    "외식율": 70,
    "건물이용율": 40,
    "점유율": 6.7,
    "일일수요": 260,
    "주변좌석수": 2500,
    "공급부족지수": 8.2,
    "공급부족등급": "★★★★★"
  },
  "재무": {
    "보수적": {"월매출": 51750000, "월순익": -900000, "BEP": 53250000, "투자회수": null, "ROI2년": null},
    "기본": {"월매출": 69000000, "월순익": 12900000, "BEP": 53250000, "투자회수": 40, "ROI2년": 40},
    "낙관적": {"월매출": 86250000, "월순익": 19800000, "BEP": 53250000, "투자회수": 26, "ROI2년": 91}
  },
  "종합": {
    "점수": 67,
    "등급": "★★★☆☆",
    "권고": "조건부 입점 권장",
    "핵심조건": "렌트프리 3개월 이상 협상 필수, 카페/캐주얼 F&B 업종 고수",
    "리스크": "보수적 시나리오에서 적자 가능, 투자회수 40개월 장기"
  }
}
